dotenv_cli/__init__.py
dotenv_cli/cli.py
dotenv_cli/core.py
dotenv_cli/version.py
dotenv_cli-3.4.1.dist-info/LICENSE
dotenv_cli-3.4.1.dist-info/METADATA
dotenv_cli-3.4.1.dist-info/WHEEL
dotenv_cli-3.4.1.dist-info/entry_points.txt
dotenv_cli-3.4.1.dist-info/top_level.txt
dotenv_cli-3.4.1.dist-info/RECORD
