Metadata-Version: 2.1
Name: dotenv-cli
Version: 3.4.1
Summary: Simple dotenv CLI.
Author-email: Bastian Venthur <mail@venthur.de>
License: MIT License
Project-URL: Documentation, https://dotenv-cli.readthedocs.io/
Project-URL: Source, https://github.com/venthur/dotenv-cli
Project-URL: Changelog, https://github.com/venthur/dotenv-cli/blob/master/CHANGELOG.md
Keywords: dotenv,cli,.env
Classifier: Development Status :: 5 - Production/Stable
Classifier: Intended Audience :: Developers
Classifier: License :: OSI Approved :: MIT License
Classifier: Programming Language :: Python :: 3
Requires-Python: >=3.9
License-File: LICENSE
Provides-Extra: dev
Requires-Dist: build; extra == "dev"
Requires-Dist: mkdocs; extra == "dev"
Requires-Dist: mkdocs-material; extra == "dev"
Requires-Dist: mypy; extra == "dev"
Requires-Dist: pytest; extra == "dev"
Requires-Dist: pytest-cov; extra == "dev"
Requires-Dist: ruff; extra == "dev"
Requires-Dist: twine; extra == "dev"
